QubitGuard/__init__.py
QubitGuard/cli.py
QubitGuard/crypto_manager.py
QubitGuard-0.1.0.dist-info/LICENSE
QubitGuard-0.1.0.dist-info/METADATA
QubitGuard-0.1.0.dist-info/WHEEL
QubitGuard-0.1.0.dist-info/dependency_links.txt
QubitGuard-0.1.0.dist-info/entry_points.txt
QubitGuard-0.1.0.dist-info/top_level.txt
QubitGuard-0.1.0.dist-info/RECORD
